ppac/REQUIREMENTS
ppac/VERSION
ppac/__init__.py
ppac/item.py
ppac/utils.py
ppac/loaders/__init__.py
ppac/loaders/jira.py
ppac-0.0.3.dist-info/LICENSE
ppac-0.0.3.dist-info/METADATA
ppac-0.0.3.dist-info/WHEEL
ppac-0.0.3.dist-info/top_level.txt
ppac-0.0.3.dist-info/RECORD
